xiaohongshumcp/__init__.py
xiaohongshumcp/__main__.py
xiaohongshumcp/py.typed
xiaohongshumcp/xiaohongshu.py
xiaohongshumcp-0.1.0.dist-info/METADATA
xiaohongshumcp-0.1.0.dist-info/WHEEL
xiaohongshumcp-0.1.0.dist-info/entry_points.txt
xiaohongshumcp-0.1.0.dist-info/RECORD
