Metadata-Version: 2.4
Name: xiaohongshumcp
Version: 0.1.0
Summary: Add your description here
Author-email: warriorsChampion <11158048+warriorschampion@user.noreply.gitee.com>
Requires-Python: >=3.12
Requires-Dist: build>=1.2.2.post1
Requires-Dist: mcp[cli]>=1.9.4
Requires-Dist: twine>=6.1.0
